README.rst
setup.py
bin/param-medic
param_medic.egg-info/PKG-INFO
param_medic.egg-info/SOURCES.txt
param_medic.egg-info/dependency_links.txt
param_medic.egg-info/requires.txt
param_medic.egg-info/top_level.txt
parammedic/__init__.py
parammedic/errorcalc.py
parammedic/mixturemodel.pyx
parammedic/ms2_io.py
parammedic/mzml_io.py
parammedic/version.py