Metadata-Version: 1.1
Name: param-medic
Version: 0.2
Summary: Param-Medic optimizes MS/MS search parameter settings.
Home-page: UNKNOWN
Author: Damon May
Author-email: damonmay@uw.edu
License: Apache
Keywords: proteomics LC-MS/MS MS/MS spectrometry
Platform: UNKNOWN
Classifier: Development Status :: 4 - Beta
Classifier: Topic :: Scientific/Engineering :: Bio-Informatics
Classifier: Intended Audience :: Science/Research
Classifier: License :: OSI Approved :: Apache Software License
Classifier: Programming Language :: Python :: 2
Classifier: Programming Language :: Python :: 2.7
